setup.cfg
setup.py
mmh/__init__.py
mmh/continuum.py
mmh/hash_f.c
mmh/mmh_version.py
mmh.egg-info/PKG-INFO
mmh.egg-info/SOURCES.txt
mmh.egg-info/dependency_links.txt
mmh.egg-info/entry_points.txt
mmh.egg-info/top_level.txt