Metadata-Version: 1.0
Name: mmh
Version: 2.2
Summary: Python bindings for Google Murmurhash2 hash algorithm
Home-page: https://github.com/airhuman/py_mmh.git
Author: Michael Lee
Author-email: liyong19861014@gmail.com
License: UNKNOWN
Platform: UNKNOWN
